LICENSE.md
README.md
setup.py
mwe_query/__init__.py
mwe_query/__main__.py
mwe_query/adpositions.py
mwe_query/alternatives.py
mwe_query/analyseducame.py
mwe_query/analyseresults.py
mwe_query/annotatetreebank.py
mwe_query/annotations.py
mwe_query/basex_query.py
mwe_query/canonicalform.py
mwe_query/celexlexiconstandin.py
mwe_query/classifymwes.py
mwe_query/conf.py
mwe_query/dcm2pep.py
mwe_query/getalpinomwes.py
mwe_query/getalpinomwus.py
mwe_query/getmwestructure.py
mwe_query/gramconfig.py
mwe_query/indexes.py
mwe_query/indextransform.py
mwe_query/lcat.py
mwe_query/mkhtml.py
mwe_query/mkpivothtmls.py
mwe_query/mkreffile.py
mwe_query/mwe_annotate.py
mwe_query/mwemeta.py
mwe_query/mweregressiontest.py
mwe_query/mwestats.py
mwe_query/mwetypes.py
mwe_query/mwetyping.py
mwe_query/mwus.py
mwe_query/mwuwordlemmas.py
mwe_query/pronadvs.py
mwe_query/py.typed
mwe_query/releaseDUCAME.py
mwe_query/rwq.py
mwe_query/self_findtest.py
mwe_query/showtree.py
mwe_query/summarize.py
mwe_query/tbfstandin.py
mwe_query/testmwequery.py
mwe_query/tryalpinomwes.py
mwe_query/tryannotate.py
mwe_query/trycontainsalllemmas.py
mwe_query/trylcat.py
mwe_query/trymwes.py
mwe_query/trymwus.py
mwe_query/trypivots.py
mwe_query/trypreprocess.py
mwe_query/tryquery4.py
mwe_query/tryremoveud.py
mwe_query/trystats.py
mwe_query/trysvps.py
mwe_query/tryxpathquery.py
mwe_query/typefunctions.py
mwe_query.egg-info/PKG-INFO
mwe_query.egg-info/SOURCES.txt
mwe_query.egg-info/dependency_links.txt
mwe_query.egg-info/entry_points.txt
mwe_query.egg-info/requires.txt
mwe_query.egg-info/top_level.txt
mwe_query.egg-info/zip-safe
tests/test_expand.py
tests/test_generate.py
tests/test_mwestats.py
tests/test_preprocess.py