Metadata-Version: 2.1
Name: mwe-query
Version: 0.1.0
Home-page: https://github.com/CentreForDigitalHumanities/mwe-query
Author: Martin Kroon / Digital Humanities Lab, Utrecht University
Author-email: digitalhumanities@uu.nl
License: CC BY-NC-SA 4.0
Requires-Python: >=3.8, <4
License-File: LICENSE.md
